{
  "_fv": 69,
  "_type": "gui",
  "definition": {
    "type": 1,
    "width": 176,
    "height": 166,
    "inventoryOffsetX": 0,
    "inventoryOffsetY": 0,
    "renderBgLayer": true,
    "doesPauseGame": false,
    "components": [
      {
        "type": "label",
        "data": {
          "name": "label_you_just_got_fanum_taxed",
          "text": {
            "fixedValue": "YOU JUST GOT FANUM TAXED!"
          },
          "color": {
            "value": -13950157,
            "falpha": 0.0
          },
          "x": 151,
          "y": 40
        }
      },
      {
        "type": "inputslot",
        "data": {
          "inputLimit": {
            "value": ""
          },
          "disablePlacement": {
            "fixedValue": false
          },
          "color": {
            "value": -7569762,
            "falpha": 0.0
          },
          "id": 0,
          "disablePickup": {
            "fixedValue": false
          },
          "dropItemsWhenNotBound": false,
          "x": 173,
          "y": 61
        }
      },
      {
        "type": "inputslot",
        "data": {
          "inputLimit": {
            "value": ""
          },
          "disablePlacement": {
            "fixedValue": false
          },
          "color": {
            "value": -8885371,
            "falpha": 0.0
          },
          "id": 1,
          "disablePickup": {
            "fixedValue": false
          },
          "dropItemsWhenNotBound": false,
          "x": 173,
          "y": 86
        }
      },
      {
        "type": "outputslot",
        "data": {
          "color": {
            "value": -11780264,
            "falpha": 0.0
          },
          "id": 2,
          "disablePickup": {
            "fixedValue": false
          },
          "dropItemsWhenNotBound": false,
          "x": 234,
          "y": 75
        }
      },
      {
        "type": "label",
        "data": {
          "name": "label_insert_money_to_pay_your_fanum_t",
          "text": {
            "fixedValue": "Insert Money To Pay Your Taxes!"
          },
          "color": {
            "value": -11978669,
            "falpha": 0.0
          },
          "x": 132,
          "y": 110
        }
      }
    ],
    "gridSettings": {
      "sx": 18,
      "sy": 18,
      "ox": 11,
      "oy": 15,
      "snapOnGrid": false
    }
  }
}